{
  "asOf": "2026-05-24T07:45:07.311Z",
  "method": "heuristic v1: β + relative-strength momentum + stage runway − valuation ceiling + catalyst (no mean-reversion). Coarse (0.5%p); trust sign/bucket.",
  "benchmarks": {
    "aN": "QQQ",
    "aK": "^KS200"
  },
  "quotes": {
    "MRVL": {
      "aN": [
        2,
        10,
        4
      ],
      "aK": [
        1,
        10,
        3.5
      ]
    },
    "005930": {
      "aN": [
        1,
        7,
        0
      ],
      "aK": [
        0.5,
        1.5,
        0
      ]
    },
    "MU": {
      "aN": [
        0.5,
        10,
        0
      ],
      "aK": [
        -0.5,
        6.5,
        0
      ]
    },
    "LITE": {
      "aN": [
        -0.5,
        4.5,
        0
      ],
      "aK": [
        -1.5,
        -1,
        0
      ]
    },
    "TSLA": {
      "aN": [
        0,
        -1.5,
        4
      ],
      "aK": [
        -1,
        -6.5,
        3.5
      ]
    },
    "VRT": {
      "aN": [
        -2.5,
        3,
        0.5
      ],
      "aK": [
        -3,
        -2.5,
        0.5
      ]
    },
    "BE": {
      "aN": [
        1.5,
        10,
        -1
      ],
      "aK": [
        0.5,
        8.5,
        -0.5
      ]
    },
    "ALAB": {
      "aN": [
        3,
        10,
        4
      ],
      "aK": [
        3,
        10,
        3.5
      ]
    },
    "AMD": {
      "aN": [
        2,
        10,
        3.5
      ],
      "aK": [
        1,
        10,
        3
      ]
    },
    "SNDK": {
      "aN": [
        1,
        10,
        5.5
      ],
      "aK": [
        0,
        10,
        5
      ]
    },
    "RMBS": {
      "aN": [
        2.5,
        8.5,
        5
      ],
      "aK": [
        1.5,
        2.5,
        4.5
      ]
    },
    "SMCI": {
      "aN": [
        2.5,
        -0.5,
        1.5
      ],
      "aK": [
        1.5,
        -5.5,
        1.5
      ]
    },
    "COHR": {
      "aN": [
        -0.5,
        7.5,
        0.5
      ],
      "aK": [
        -1,
        1.5,
        0.5
      ]
    },
    "VICR": {
      "aN": [
        -0.5,
        10,
        7
      ],
      "aK": [
        -1.5,
        4,
        6.5
      ]
    },
    "CEG": {
      "aN": [
        1.5,
        -2.5,
        4.5
      ],
      "aK": [
        1,
        -8,
        4
      ]
    },
    "OKLO": {
      "aN": [
        1,
        -0.5,
        8.5
      ],
      "aK": [
        0,
        -5.5,
        7.5
      ]
    },
    "QCOM": {
      "aN": [
        3,
        10,
        1.5
      ],
      "aK": [
        2.5,
        5,
        1.5
      ]
    }
  }
}